{
  "unversionedId": "inputv0.3",
  "id": "inputv0.3",
  "title": "Input Board v0.3",
  "description": "Input Board BBB",
  "source": "@site/boards/03-inputv0.3.md",
  "sourceDirName": ".",
  "slug": "/inputv0.3",
  "permalink": "/boards/inputv0.3",
  "tags": [],
  "version": "current",
  "lastUpdatedBy": "Author",
  "lastUpdatedAt": 1539502055,
  "formattedLastUpdatedAt": "10/14/2018",
  "sidebarPosition": 3,
  "frontMatter": {
    "sidebar_position": 3
  },
  "sidebar": "tutorialSidebar",
  "previous": {
    "title": "Intro",
    "permalink": "/boards/"
  },
  "next": {
    "title": "Input Board v0.2",
    "permalink": "/boards/v0.2/inputv0.2"
  }
}